sigmaepsilon/solid/fourier/__init__.py
sigmaepsilon/solid/fourier/beam.py
sigmaepsilon/solid/fourier/config.py
sigmaepsilon/solid/fourier/enums.py
sigmaepsilon/solid/fourier/loads/__init__.py
sigmaepsilon/solid/fourier/loads/diskload.py
sigmaepsilon/solid/fourier/loads/lineload.py
sigmaepsilon/solid/fourier/loads/loads.py
sigmaepsilon/solid/fourier/loads/pointload.py
sigmaepsilon/solid/fourier/loads/rectangleload.py
sigmaepsilon/solid/fourier/mc.py
sigmaepsilon/solid/fourier/plate.py
sigmaepsilon/solid/fourier/postproc.py
sigmaepsilon/solid/fourier/preproc.py
sigmaepsilon/solid/fourier/problem.py
sigmaepsilon/solid/fourier/proc.py
sigmaepsilon/solid/fourier/protocols.py
sigmaepsilon/solid/fourier/result.py
sigmaepsilon/solid/fourier/utils.py
sigmaepsilon_solid_fourier-2.1.3.dist-info/LICENSE
sigmaepsilon_solid_fourier-2.1.3.dist-info/METADATA
sigmaepsilon_solid_fourier-2.1.3.dist-info/WHEEL
sigmaepsilon_solid_fourier-2.1.3.dist-info/RECORD
