Metadata-Version: 2.3
Name: sigmaepsilon.solid.fourier
Version: 2.1.3
Summary: Fourier solutions of some plate and beam bending problems in Python
License: MIT
Keywords: engineering,fourier,benchmark,mechanics,solid mechanics,elasticity,mindlin,kirchhoff,euler,timoshenko,beam,plate,uflyand,bernoulli,bensys,programming,Python
Author: Bence Balogh
Author-email: bencebalogh@sigmaepsilon.com
Maintainer: Bence Balogh
Maintainer-email: bencebalogh@sigmaepsilon.com
Requires-Python: >=3.10,<3.13
Classifier: Development Status :: 5 - Production/Stable
Classifier: License :: OSI Approved :: MIT License
Classifier: Operating System :: OS Independent
Classifier: Programming Language :: Python :: 3
Classifier: Programming Language :: Python :: 3.10
Classifier: Programming Language :: Python :: 3.11
Classifier: Programming Language :: Python :: 3.12
Classifier: Programming Language :: Python :: 3 :: Only
Requires-Dist: sigmaepsilon-deepdict (>=2.0.0,<3.0.0)
Requires-Dist: sigmaepsilon-mesh (>=3.0.2,<4.0.0)
Requires-Dist: sigmaepsilon-solid-material (>=1.0.2,<2.0.0)
Project-URL: Documentation, https://sigmaepsilonsolidfourier.readthedocs.io/en/latest/?badge=latest
Project-URL: Homepage, https://github.com/sigma-epsilon/sigmaepsilon.solid.fourier
Project-URL: Repository, https://github.com/sigma-epsilon/sigmaepsilon.solid.fourier
